transparentapi/__init__.py
transparentapi/api.py
transparentapi/exceptions.py
transparentapi/projects.py
transparentapi/tasks.py
transparentapi/utils.py
transparentapi-0.1.1.dist-info/LICENSE
transparentapi-0.1.1.dist-info/METADATA
transparentapi-0.1.1.dist-info/WHEEL
transparentapi-0.1.1.dist-info/top_level.txt
transparentapi-0.1.1.dist-info/RECORD
